capybre/__init__.py
capybre/convert.py
capybre/ebook_format.py
capybre/fetch_metadata.py
capybre/helpers.py
capybre/metadata.py
capybre-0.0.6.dist-info/LICENSE
capybre-0.0.6.dist-info/METADATA
capybre-0.0.6.dist-info/WHEEL
capybre-0.0.6.dist-info/top_level.txt
capybre-0.0.6.dist-info/RECORD
