Metadata-Version: 2.1
Name: capybre
Version: 0.0.6
Summary: Python interface for Calibre's command line tools
Home-page: http://github.com/digitaltembo/capybre
Author: Nolan Hawkins
Author-email: nolanhhawkins@gmail.com
License: MIT
Platform: UNKNOWN
Classifier: Programming Language :: Python :: 3
Classifier: License :: OSI Approved :: MIT License
Classifier: Operating System :: OS Independent
Requires-Python: >=3.6
